plotmat/__init__.py
plotmat-0.0.1.dist-info/LICENSE
plotmat-0.0.1.dist-info/METADATA
plotmat-0.0.1.dist-info/WHEEL
plotmat-0.0.1.dist-info/top_level.txt
plotmat-0.0.1.dist-info/RECORD
