Metadata-Version: 2.1
Name: plotmat
Version: 0.0.1
Summary: A collection of Plotting tools for Materials data from Phases Research Lab at PennState; with pieces useful to the general audience published through PyPI.
Author-email: Hui Sun <suh960@psu.edu>, Adam Krajewski <ak@psu.edu>
Project-URL: Research Page, https://phaseslab.com/
Project-URL: Bug Tracker, https://github.com/PhasesResearchLab/PlotMat/issues
Classifier: Programming Language :: Python :: 3
Classifier: Development Status :: 1 - Planning
Classifier: Intended Audience :: Science/Research
Classifier: License :: OSI Approved :: MIT License
Classifier: Operating System :: OS Independent
Classifier: Topic :: Scientific/Engineering
Classifier: Topic :: Scientific/Engineering :: Chemistry
Classifier: Topic :: Scientific/Engineering :: Physics
Requires-Python: >=3.9
License-File: LICENSE
Requires-Dist: matplotlib
Requires-Dist: plotly
